s3managerpy/__init__.py
s3managerpy/manager.py
s3managerpy-0.1.1.dist-info/licenses/LICENSE
s3managerpy-0.1.1.dist-info/METADATA
s3managerpy-0.1.1.dist-info/WHEEL
s3managerpy-0.1.1.dist-info/top_level.txt
s3managerpy-0.1.1.dist-info/RECORD
