Metadata-Version: 2.4
Name: s3managerpy
Version: 0.1.1
Summary: A clean helper class to manage AWS S3 operations in Python.
Author-email: Olusola Ayomide Victor <ayomideolusola5002@gmail.com>
License-Expression: MIT
Project-URL: Homepage, https://github.com/VictorAO-django/s3managerpy
Project-URL: Repository, https://github.com/VictorAO-django/s3managerpy.git
Classifier: Programming Language :: Python :: 3
Classifier: Programming Language :: Python :: 3.7
Classifier: Programming Language :: Python :: 3.8
Classifier: Programming Language :: Python :: 3.9
Classifier: Programming Language :: Python :: 3.10
Classifier: Programming Language :: Python :: 3.11
Classifier: Programming Language :: Python :: 3.12
Classifier: Operating System :: OS Independent
Requires-Python: >=3.7
License-File: LICENSE
Requires-Dist: boto3
Dynamic: license-file
